PyImpetus.py
PyImpetus-4.1.2.dist-info/LICENSE
PyImpetus-4.1.2.dist-info/METADATA
PyImpetus-4.1.2.dist-info/WHEEL
PyImpetus-4.1.2.dist-info/top_level.txt
PyImpetus-4.1.2.dist-info/RECORD
