Metadata-Version: 2.1
Name: PyImpetus
Version: 4.1.2
Summary: PyImpetus is a Markov Blanket based feature subset selection algorithm that considers features both separately and together as a group in order to provide not just the best set of features but also the best combination of features
Home-page: https://github.com/atif-hassan/PyImpetus
Author: Atif Hassan
Author-email: atif.hit.hassan@gmail.com
License: UNKNOWN
Platform: UNKNOWN
Classifier: Programming Language :: Python :: 3
Classifier: Programming Language :: Python :: 3.6
Classifier: Programming Language :: Python :: 3.7
Classifier: Operating System :: OS Independent
License-File: LICENSE
Requires-Dist: pandas
Requires-Dist: scikit-learn
Requires-Dist: numpy
Requires-Dist: joblib
